mstardna/__init__.py
mstardna-0.1.1.dist-info/WHEEL
mstardna-0.1.1.dist-info/METADATA
mstardna-0.1.1.dist-info/RECORD
