Metadata-Version: 2.1
Name: mstardna
Version: 0.1.1
Summary: 
Author: Jinyoung Kim
Author-email: jinyoung.kim@morningstar.com
Requires-Python: >=3.7,<4.0
Classifier: Programming Language :: Python :: 3
Classifier: Programming Language :: Python :: 3.7
Classifier: Programming Language :: Python :: 3.8
Requires-Dist: boto3 (>=1.14.42,<2.0.0)
